{"frames":{"images/session/abilities/fx/nature_beam.png":{"frame":{"x":2,"y":2,"w":1263,"h":920},"rotated":false,"trimmed":true,"spriteSourceSize":{"x":62,"y":0,"w":1263,"h":920},"sourceSize":{"w":1350,"h":920},"pivot":{"x":0.5,"y":0.5}},"images/session/abilities/fx/ion_beam.png":{"frame":{"x":2,"y":926,"w":1259,"h":938},"rotated":false,"trimmed":true,"spriteSourceSize":{"x":9,"y":0,"w":1259,"h":938},"sourceSize":{"w":1280,"h":940},"pivot":{"x":0.5,"y":0.5}},"embeded-images/splash/bg.png":{"frame":{"x":1269,"y":2,"w":640,"h":1136},"rotated":false,"trimmed":false,"spriteSourceSize":{"x":0,"y":0,"w":640,"h":1136},"sourceSize":{"w":640,"h":1136},"pivot":{"x":0.5,"y":0.5}},"images/session/ui/card_use_miss.png":{"frame":{"x":2,"y":1868,"w":990,"h":161},"rotated":false,"trimmed":true,"spriteSourceSize":{"x":25,"y":0,"w":990,"h":161},"sourceSize":{"w":1020,"h":170},"pivot":{"x":0.5,"y":0.5}},"images/map/hub/clouds_far.png":{"frame":{"x":996,"y":1868,"w":943,"h":148},"rotated":false,"trimmed":false,"spriteSourceSize":{"x":0,"y":0,"w":943,"h":148},"sourceSize":{"w":943,"h":148},"pivot":{"x":0.5,"y":0.5}},"images/session/abilities/fx/direct_aim.png":{"frame":{"x":1265,"y":1142,"w":748,"h":155},"rotated":false,"trimmed":true,"spriteSourceSize":{"x":27,"y":2,"w":748,"h":155},"sourceSize":{"w":800,"h":160},"pivot":{"x":0.5,"y":0.5}},"images/general/map_info/headers/mayan_temple.png":{"frame":{"x":1265,"y":1301,"w":640,"h":172},"rotated":false,"trimmed":false,"spriteSourceSize":{"x":0,"y":0,"w":640,"h":172},"sourceSize":{"w":640,"h":172},"pivot":{"x":0.5,"y":0.5}},"images/general/map_info/headers/tallpines.png":{"frame":{"x":1265,"y":1477,"w":640,"h":172},"rotated":false,"trimmed":false,"spriteSourceSize":{"x":0,"y":0,"w":640,"h":172},"sourceSize":{"w":640,"h":172},"pivot":{"x":0.5,"y":0.5}},"images/general/map_info/headers/volcano.png":{"frame":{"x":1265,"y":1653,"w":640,"h":172},"rotated":false,"trimmed":false,"spriteSourceSize":{"x":0,"y":0,"w":640,"h":172},"sourceSize":{"w":640,"h":172},"pivot":{"x":0.5,"y":0.5}},"images/general/huds/pane_mini_fire.png":{"frame":{"x":1913,"y":2,"w":128,"h":154},"rotated":false,"trimmed":true,"spriteSourceSize":{"x":1,"y":3,"w":128,"h":154},"sourceSize":{"w":130,"h":160},"pivot":{"x":0.5,"y":0.5}},"images/general/huds/pane_mini_water.png":{"frame":{"x":1913,"y":160,"w":128,"h":154},"rotated":false,"trimmed":true,"spriteSourceSize":{"x":1,"y":3,"w":128,"h":154},"sourceSize":{"w":130,"h":160},"pivot":{"x":0.5,"y":0.5}},"images/general/icon_aim.png":{"frame":{"x":1909,"y":1301,"w":136,"h":48},"rotated":false,"trimmed":true,"spriteSourceSize":{"x":0,"y":8,"w":136,"h":48},"sourceSize":{"w":150,"h":60},"pivot":{"x":0.5,"y":0.5}},"images/general/error_modal/icon_update.png":{"frame":{"x":1913,"y":318,"w":133,"h":127},"rotated":false,"trimmed":true,"spriteSourceSize":{"x":13,"y":5,"w":133,"h":127},"sourceSize":{"w":150,"h":141},"pivot":{"x":0.5,"y":0.5}},"images/general/error_modal/icon_generic.png":{"frame":{"x":1913,"y":449,"w":132,"h":120},"rotated":false,"trimmed":true,"spriteSourceSize":{"x":4,"y":5,"w":132,"h":120},"sourceSize":{"w":140,"h":130},"pivot":{"x":0.5,"y":0.5}},"images/general/error_modal/icon_dc.png":{"frame":{"x":1913,"y":573,"w":131,"h":130},"rotated":false,"trimmed":true,"spriteSourceSize":{"x":5,"y":5,"w":131,"h":130},"sourceSize":{"w":140,"h":140},"pivot":{"x":0.5,"y":0.5}},"images/general/error_modal/icon_internet.png":{"frame":{"x":1913,"y":707,"w":131,"h":130},"rotated":false,"trimmed":true,"spriteSourceSize":{"x":5,"y":5,"w":131,"h":130},"sourceSize":{"w":140,"h":140},"pivot":{"x":0.5,"y":0.5}},"images/session/endscreen/btn_later.png":{"frame":{"x":1913,"y":841,"w":131,"h":54},"rotated":false,"trimmed":true,"spriteSourceSize":{"x":10,"y":8,"w":131,"h":54},"sourceSize":{"w":150,"h":70},"pivot":{"x":0.5,"y":0.5}},"images/team/info/btn_release.png":{"frame":{"x":1913,"y":899,"w":131,"h":54},"rotated":false,"trimmed":true,"spriteSourceSize":{"x":10,"y":8,"w":131,"h":54},"sourceSize":{"w":150,"h":70},"pivot":{"x":0.5,"y":0.5}},"images/session/abilities/mega_border.png":{"frame":{"x":1913,"y":957,"w":130,"h":130},"rotated":false,"trimmed":false,"spriteSourceSize":{"x":0,"y":0,"w":130,"h":130},"sourceSize":{"w":130,"h":130},"pivot":{"x":0.5,"y":0.5}},"images/session/ui/discatch_glow.png":{"frame":{"x":1909,"y":1353,"w":115,"h":121},"rotated":false,"trimmed":true,"spriteSourceSize":{"x":43,"y":43,"w":115,"h":121},"sourceSize":{"w":201,"h":207},"pivot":{"x":0.5,"y":0.5}},"images/map/btn_items_off.png":{"frame":{"x":1909,"y":1478,"w":111,"h":120},"rotated":false,"trimmed":true,"spriteSourceSize":{"x":5,"y":0,"w":111,"h":120},"sourceSize":{"w":120,"h":130},"pivot":{"x":0.5,"y":0.5}},"images/session/ui/btn_escape.png":{"frame":{"x":1909,"y":1602,"w":111,"h":119},"rotated":false,"trimmed":true,"spriteSourceSize":{"x":5,"y":8,"w":111,"h":119},"sourceSize":{"w":120,"h":130},"pivot":{"x":0.5,"y":0.5}},"images/items/item_selected.png":{"frame":{"x":1909,"y":1725,"w":118,"h":118},"rotated":false,"trimmed":true,"spriteSourceSize":{"x":1,"y":1,"w":118,"h":118},"sourceSize":{"w":120,"h":120},"pivot":{"x":0.5,"y":0.5}},"images/general/reward_slot.png":{"frame":{"x":1943,"y":1847,"w":101,"h":102},"rotated":false,"trimmed":true,"spriteSourceSize":{"x":4,"y":4,"w":101,"h":102},"sourceSize":{"w":110,"h":110},"pivot":{"x":0.5,"y":0.5}},"images/session/ui/icon_rage.png":{"frame":{"x":1913,"y":1091,"w":90,"h":41},"rotated":false,"trimmed":true,"spriteSourceSize":{"x":5,"y":0,"w":90,"h":41},"sourceSize":{"w":100,"h":50},"pivot":{"x":0.5,"y":0.5}},"images/items/icons/coins.png":{"frame":{"x":1943,"y":1953,"w":87,"h":73},"rotated":false,"trimmed":true,"spriteSourceSize":{"x":2,"y":5,"w":87,"h":73},"sourceSize":{"w":90,"h":80},"pivot":{"x":0.5,"y":0.5}},"images/dynapedia/questionmark.png":{"frame":{"x":2007,"y":1091,"w":39,"h":39},"rotated":false,"trimmed":false,"spriteSourceSize":{"x":0,"y":0,"w":39,"h":39},"sourceSize":{"w":39,"h":39},"pivot":{"x":0.5,"y":0.5}},"images/fonts/red_stroked_small/c38.png":{"frame":{"x":1265,"y":1829,"w":33,"h":30},"rotated":false,"trimmed":true,"spriteSourceSize":{"x":4,"y":4,"w":33,"h":30},"sourceSize":{"w":40,"h":40},"pivot":{"x":0.5,"y":0.5}},"images/fonts/white_stroked_big/c104.png":{"frame":{"x":1302,"y":1829,"w":23,"h":33},"rotated":false,"trimmed":true,"spriteSourceSize":{"x":0,"y":8,"w":23,"h":33},"sourceSize":{"w":23,"h":50},"pivot":{"x":0.5,"y":0.5}},"images/fonts/white_stroked_big/c107.png":{"frame":{"x":1329,"y":1829,"w":24,"h":33},"rotated":false,"trimmed":true,"spriteSourceSize":{"x":0,"y":8,"w":24,"h":33},"sourceSize":{"w":24,"h":50},"pivot":{"x":0.5,"y":0.5}},"images/fonts/white_stroked_big/c98.png":{"frame":{"x":1357,"y":1829,"w":23,"h":33},"rotated":false,"trimmed":true,"spriteSourceSize":{"x":0,"y":8,"w":23,"h":33},"sourceSize":{"w":23,"h":50},"pivot":{"x":0.5,"y":0.5}},"images/fonts/red_stroked_big/c48.png":{"frame":{"x":1384,"y":1829,"w":24,"h":32},"rotated":false,"trimmed":true,"spriteSourceSize":{"x":0,"y":9,"w":24,"h":32},"sourceSize":{"w":24,"h":50},"pivot":{"x":0.5,"y":0.5}},"images/fonts/red_stroked_big/c50.png":{"frame":{"x":2024,"y":1478,"w":22,"h":32},"rotated":false,"trimmed":true,"spriteSourceSize":{"x":0,"y":9,"w":22,"h":32},"sourceSize":{"w":22,"h":50},"pivot":{"x":0.5,"y":0.5}},"images/fonts/red_stroked_big/c51.png":{"frame":{"x":2024,"y":1514,"w":22,"h":32},"rotated":false,"trimmed":true,"spriteSourceSize":{"x":0,"y":9,"w":22,"h":32},"sourceSize":{"w":22,"h":50},"pivot":{"x":0.5,"y":0.5}},"images/fonts/red_stroked_big/c52.png":{"frame":{"x":2017,"y":1134,"w":27,"h":32},"rotated":false,"trimmed":true,"spriteSourceSize":{"x":0,"y":9,"w":27,"h":32},"sourceSize":{"w":27,"h":50},"pivot":{"x":0.5,"y":0.5}},"images/fonts/red_stroked_big/c54.png":{"frame":{"x":1412,"y":1829,"w":24,"h":32},"rotated":false,"trimmed":true,"spriteSourceSize":{"x":0,"y":9,"w":24,"h":32},"sourceSize":{"w":24,"h":50},"pivot":{"x":0.5,"y":0.5}},"images/fonts/red_stroked_big/c55.png":{"frame":{"x":1440,"y":1829,"w":23,"h":32},"rotated":false,"trimmed":true,"spriteSourceSize":{"x":0,"y":9,"w":23,"h":32},"sourceSize":{"w":23,"h":50},"pivot":{"x":0.5,"y":0.5}},"images/fonts/red_stroked_big/c56.png":{"frame":{"x":1467,"y":1829,"w":24,"h":32},"rotated":false,"trimmed":true,"spriteSourceSize":{"x":0,"y":9,"w":24,"h":32},"sourceSize":{"w":24,"h":50},"pivot":{"x":0.5,"y":0.5}},"images/fonts/red_stroked_big/c57.png":{"frame":{"x":1495,"y":1829,"w":24,"h":32},"rotated":false,"trimmed":true,"spriteSourceSize":{"x":0,"y":9,"w":24,"h":32},"sourceSize":{"w":24,"h":50},"pivot":{"x":0.5,"y":0.5}},"images/fonts/white_stroked_big/c112.png":{"frame":{"x":1523,"y":1829,"w":23,"h":32},"rotated":false,"trimmed":true,"spriteSourceSize":{"x":0,"y":14,"w":23,"h":32},"sourceSize":{"w":23,"h":50},"pivot":{"x":0.5,"y":0.5}},"images/fonts/white_stroked_big/c113.png":{"frame":{"x":1550,"y":1829,"w":24,"h":32},"rotated":false,"trimmed":true,"spriteSourceSize":{"x":0,"y":14,"w":24,"h":32},"sourceSize":{"w":24,"h":50},"pivot":{"x":0.5,"y":0.5}},"images/fonts/white_stroked_big/c121.png":{"frame":{"x":1578,"y":1829,"w":24,"h":32},"rotated":false,"trimmed":true,"spriteSourceSize":{"x":0,"y":15,"w":24,"h":32},"sourceSize":{"w":24,"h":50},"pivot":{"x":0.5,"y":0.5}},"images/fonts/white_stroked_big/c35.png":{"frame":{"x":1606,"y":1829,"w":32,"h":31},"rotated":false,"trimmed":true,"spriteSourceSize":{"x":0,"y":10,"w":32,"h":31},"sourceSize":{"w":32,"h":50},"pivot":{"x":0.5,"y":0.5}},"images/fonts/white_stroked_big/c48.png":{"frame":{"x":1642,"y":1829,"w":24,"h":32},"rotated":false,"trimmed":true,"spriteSourceSize":{"x":0,"y":9,"w":24,"h":32},"sourceSize":{"w":24,"h":50},"pivot":{"x":0.5,"y":0.5}},"images/fonts/white_stroked_big/c50.png":{"frame":{"x":1670,"y":1829,"w":23,"h":32},"rotated":false,"trimmed":true,"spriteSourceSize":{"x":0,"y":9,"w":23,"h":32},"sourceSize":{"w":23,"h":50},"pivot":{"x":0.5,"y":0.5}},"images/fonts/white_stroked_big/c51.png":{"frame":{"x":1697,"y":1829,"w":23,"h":32},"rotated":false,"trimmed":true,"spriteSourceSize":{"x":0,"y":9,"w":23,"h":32},"sourceSize":{"w":23,"h":50},"pivot":{"x":0.5,"y":0.5}},"images/fonts/white_stroked_big/c52.png":{"frame":{"x":2017,"y":1170,"w":26,"h":32},"rotated":false,"trimmed":true,"spriteSourceSize":{"x":0,"y":9,"w":26,"h":32},"sourceSize":{"w":26,"h":50},"pivot":{"x":0.5,"y":0.5}},"images/fonts/white_stroked_big/c53.png":{"frame":{"x":2024,"y":1550,"w":22,"h":32},"rotated":false,"trimmed":true,"spriteSourceSize":{"x":0,"y":9,"w":22,"h":32},"sourceSize":{"w":22,"h":50},"pivot":{"x":0.5,"y":0.5}},"images/fonts/white_stroked_big/c54.png":{"frame":{"x":1724,"y":1829,"w":24,"h":32},"rotated":false,"trimmed":true,"spriteSourceSize":{"x":0,"y":9,"w":24,"h":32},"sourceSize":{"w":24,"h":50},"pivot":{"x":0.5,"y":0.5}},"images/fonts/white_stroked_big/c55.png":{"frame":{"x":1752,"y":1829,"w":23,"h":32},"rotated":false,"trimmed":true,"spriteSourceSize":{"x":0,"y":9,"w":23,"h":32},"sourceSize":{"w":23,"h":50},"pivot":{"x":0.5,"y":0.5}},"images/fonts/white_stroked_big/c56.png":{"frame":{"x":1779,"y":1829,"w":24,"h":32},"rotated":false,"trimmed":true,"spriteSourceSize":{"x":0,"y":9,"w":24,"h":32},"sourceSize":{"w":24,"h":50},"pivot":{"x":0.5,"y":0.5}},"images/fonts/white_stroked_big/c57.png":{"frame":{"x":1807,"y":1829,"w":24,"h":32},"rotated":false,"trimmed":true,"spriteSourceSize":{"x":0,"y":9,"w":24,"h":32},"sourceSize":{"w":24,"h":50},"pivot":{"x":0.5,"y":0.5}},"images/fonts/white_stroked_big/c65.png":{"frame":{"x":2017,"y":1206,"w":26,"h":32},"rotated":false,"trimmed":true,"spriteSourceSize":{"x":0,"y":9,"w":26,"h":32},"sourceSize":{"w":26,"h":50},"pivot":{"x":0.5,"y":0.5}},"images/fonts/white_stroked_big/c66.png":{"frame":{"x":1835,"y":1829,"w":24,"h":32},"rotated":false,"trimmed":true,"spriteSourceSize":{"x":0,"y":9,"w":24,"h":32},"sourceSize":{"w":24,"h":50},"pivot":{"x":0.5,"y":0.5}},"images/fonts/white_stroked_big/c67.png":{"frame":{"x":1863,"y":1829,"w":23,"h":32},"rotated":false,"trimmed":true,"spriteSourceSize":{"x":0,"y":9,"w":23,"h":32},"sourceSize":{"w":23,"h":50},"pivot":{"x":0.5,"y":0.5}},"images/fonts/white_stroked_big/c68.png":{"frame":{"x":2017,"y":1242,"w":26,"h":32},"rotated":false,"trimmed":true,"spriteSourceSize":{"x":0,"y":9,"w":26,"h":32},"sourceSize":{"w":26,"h":50},"pivot":{"x":0.5,"y":0.5}},"images/fonts/white_stroked_small/c37.png":{"frame":{"x":996,"y":2020,"w":27,"h":25},"rotated":false,"trimmed":true,"spriteSourceSize":{"x":0,"y":7,"w":27,"h":25},"sourceSize":{"w":27,"h":40},"pivot":{"x":0.5,"y":0.5}},"images/fonts/white_stroked_big/c118.png":{"frame":{"x":1027,"y":2020,"w":25,"h":26},"rotated":false,"trimmed":true,"spriteSourceSize":{"x":0,"y":15,"w":25,"h":26},"sourceSize":{"w":25,"h":50},"pivot":{"x":0.5,"y":0.5}},"images/fonts/white_stroked_big/c120.png":{"frame":{"x":1056,"y":2020,"w":23,"h":26},"rotated":false,"trimmed":true,"spriteSourceSize":{"x":0,"y":15,"w":23,"h":26},"sourceSize":{"w":23,"h":50},"pivot":{"x":0.5,"y":0.5}},"images/fonts/white_stroked_big/c42.png":{"frame":{"x":1083,"y":2020,"w":26,"h":25},"rotated":false,"trimmed":true,"spriteSourceSize":{"x":0,"y":12,"w":26,"h":25},"sourceSize":{"w":26,"h":50},"pivot":{"x":0.5,"y":0.5}},"images/splash/bg.png":{"frame":{"x":1269,"y":2,"w":640,"h":1136},"rotated":false,"trimmed":false,"spriteSourceSize":{"x":0,"y":0,"w":640,"h":1136},"sourceSize":{"w":640,"h":1136},"pivot":{"x":0.5,"y":0.5}},"images/fonts/white_stroked_small/c38.png":{"frame":{"x":1265,"y":1829,"w":33,"h":30},"rotated":false,"trimmed":true,"spriteSourceSize":{"x":4,"y":4,"w":33,"h":30},"sourceSize":{"w":40,"h":40},"pivot":{"x":0.5,"y":0.5}}},"meta":{"app":"https://github.com/odrick/grunt-free-tex-packer","version":"0.2.8","image":"atlas-5.png","format":"RGBA8888","size":{"w":2048,"h":2048},"scale":1}}